LICENSE
MANIFEST.in
README.md
setup.cfg
setup.py
intuition/__init__.py
intuition/__main__.py
intuition/cli.py
intuition/constants.py
intuition/errors.py
intuition/finance.py
intuition/test_framework.py
intuition/utils.py
intuition.egg-info/PKG-INFO
intuition.egg-info/SOURCES.txt
intuition.egg-info/dependency_links.txt
intuition.egg-info/entry_points.txt
intuition.egg-info/requires.txt
intuition.egg-info/top_level.txt
intuition/api/__init__.py
intuition/api/algorithm.py
intuition/api/context.py
intuition/api/datafeed.py
intuition/api/portfolio.py
intuition/core/__init__.py
intuition/core/analyzes.py
intuition/core/configuration.py
intuition/core/engine.py
intuition/data/__init__.py
intuition/data/data.py
intuition/data/forex.py
intuition/data/loader.py
intuition/data/quandl.py
intuition/data/remote.py
intuition/data/universe.py
intuition/data/utils.py
intuition/data/ystockquote.py